smartjson/__init__.py
smartjson/core.py
smartjson-2.1.0.dist-info/licenses/LICENSE
smartjson-2.1.0.dist-info/METADATA
smartjson-2.1.0.dist-info/WHEEL
smartjson-2.1.0.dist-info/top_level.txt
smartjson-2.1.0.dist-info/RECORD
