Metadata-Version: 2.4
Name: smartjson
Version: 2.1.0
Summary: A Python library for seamless serialization of Python objects/dictionaries to JSON and deserialization of JSON back to Python objects, with schema validation capabilities.
Home-page: https://github.com/koffiisen/SmartJson
Author: J. Koffi ONIPOH
Author-email: jolli644@gmail.com
Project-URL: Documentation, https://github.com/koffiisen/SmartJson#readme
Project-URL: Source, https://github.com/koffiisen/SmartJson
Project-URL: Tracker, https://github.com/koffiisen/SmartJson/issues
Project-URL: Changelog, https://github.com/koffiisen/SmartJson/blob/main/CHANGELOG.md
Keywords: json,serialize,deserialize,serialization,deserialization,json conversion,python to json,json to python,schema validation,object mapper,datetime,enum,complex,OrderedDict,deque
Classifier: Development Status :: 4 - Beta
Classifier: Intended Audience :: Developers
Classifier: Topic :: Software Development :: Libraries :: Python Modules
Classifier: Topic :: Utilities
Classifier: License :: OSI Approved :: MIT License
Classifier: Operating System :: OS Independent
Classifier: Programming Language :: Python
Classifier: Programming Language :: Python :: 2
Classifier: Programming Language :: Python :: 2.7
Classifier: Programming Language :: Python :: 3
Classifier: Programming Language :: Python :: 3.6
Classifier: Programming Language :: Python :: 3.7
Classifier: Programming Language :: Python :: 3.8
Classifier: Programming Language :: Python :: 3.9
Classifier: Programming Language :: Python :: 3.10
Classifier: Programming Language :: Python :: 3.11
Classifier: Programming Language :: Python :: 3.12
Requires-Python: >=2.7, !=3.0.*, !=3.1.*, !=3.2.*, !=3.3.*, !=3.4.*, !=3.5.*
License-File: LICENSE
Requires-Dist: six>=1.10.0
Requires-Dist: enum34; python_version < "3.4"
Dynamic: author
Dynamic: author-email
Dynamic: classifier
Dynamic: description
Dynamic: description-content-type
Dynamic: home-page
Dynamic: keywords
Dynamic: license-file
Dynamic: project-url
Dynamic: requires-dist
Dynamic: requires-python
Dynamic: summary
